{
  "ComponentIndexes": {
    "Controls": 9,
    "Dialogs": 10,
    "EmailFn": 3,
    "EmailFns_v1__": 6,
    "LoadingSpinner_v1__": 5,
    "LoadingSpinner_v1___1": 1,
    "ShadowRectangle_v2__": 7,
    "ShadowRectangle_v2___1": 5,
    "ShadowRectangle_v2___2": 6,
    "ShadowRectangle_v2___3": 5,
    "Toast_v2__": 8,
    "Toast_v2___1": 7
  },
  "ControlUniqueGuids": {},
  "ControlUniqueIds": {
    "App": 1,
    "btn_AcceptOwnership": 105,
    "btn_BigDanger_1": 20,
    "btn_BigDanger_2": 185,
    "btn_CancelRequestClosure": 74,
    "btn_CancelRequestedOwner": 161,
    "btn_CollapseAction": 102,
    "btn_ConfirmClosure": 100,
    "btn_ConfirmRequestClosure": 75,
    "btn_DeleteAction": 152,
    "btn_DialogCancel_1": 52,
    "btn_Edit_1": 87,
    "btn_EditAction": 97,
    "btn_EditCancel": 174,
    "btn_EditUpdate": 176,
    "btn_ExpandAction": 98,
    "btn_HomeAddAction": 79,
    "btn_LittleDanger_1": 21,
    "btn_LittleDanger_2": 188,
    "btn_Primary_1": 17,
    "btn_Primary_2": 186,
    "btn_Primary_4": 181,
    "btn_ProgressHistoryCancel": 143,
    "btn_ProgressHistoryDone": 142,
    "btn_QuickPostSend": 117,
    "btn_RejectClosure": 101,
    "btn_RejectOwnership": 106,
    "btn_ReOpen": 175,
    "btn_Secondary_1": 18,
    "btn_Secondary_2": 187,
    "btn_Tertiary_1": 19,
    "btn_Tertiary_2": 184,
    "btn_THExpandQuickPost": 91,
    "Button2": 44,
    "chk_ActionStatus": 108,
    "chk_XYZ_4": 23,
    "chk_XYZ_5": 24,
    "chk_XYZ_6": 25,
    "chk_XYZ_7": 190,
    "chk_XYZ_8": 191,
    "chk_XYZ_9": 192,
    "Container1": 8,
    "Container1_3": 42,
    "Container6": 95,
    "Controls": 11,
    "date_DatePicker_1": 33,
    "date_DatePicker_2": 198,
    "date_EditTarget": 173,
    "date_EditTarget_1": 141,
    "debug": 120,
    "dev_NavigateHome_2": 63,
    "dev_NavigateLoading_2": 123,
    "dev_StartLoading_2": 124,
    "dialog_AskSomething_1": 50,
    "dialog_RequestClosure": 66,
    "Dialogs": 48,
    "Dialogs_1": 49,
    "Dialogs_2": 65,
    "drop_EditCloser": 167,
    "drop_EditOwner": 162,
    "drop_MultiSelect_1": 31,
    "drop_MultiSelect_2": 199,
    "drop_Standard_1": 30,
    "drop_Standard_2": 195,
    "Edit": 144,
    "EditPanel": 148,
    "EmailFn": 62,
    "EmailFns_v1__": 3,
    "fn_EditActionSendEmails": 146,
    "fn_InitAppSpecificsAndFinish": 61,
    "fn_InitColors": 57,
    "fn_InitControls": 58,
    "fn_InitCore": 56,
    "fn_InitFrame": 60,
    "Gallery1": 93,
    "Gallery2": 131,
    "galleryTemplate1": 94,
    "galleryTemplate2": 132,
    "grp_Checkboxes_1": 22,
    "grp_Checkboxes_2": 189,
    "grp_Closer": 164,
    "grp_ExternalOwner": 158,
    "grp_LatestPost": 115,
    "grp_MainGallary": 80,
    "grp_OtherActionsAcceptOwnership": 104,
    "grp_OtherActionsConfirmClosure": 99,
    "grp_OtherInfo": 107,
    "grp_Owner": 109,
    "grp_Progress": 170,
    "Home": 64,
    "HtmlText1": 122,
    "HtmlText2": 4,
    "HtmlText2_3": 46,
    "Icon1": 111,
    "Icon1_3": 47,
    "Icon3_1": 27,
    "Icon3_2": 193,
    "Icon3_3": 172,
    "Icon5_2": 45,
    "Image1": 9,
    "Image1_1": 36,
    "Image1_4": 110,
    "Image1_5": 112,
    "Image1_6": 71,
    "Image1_7": 77,
    "img_Closer": 119,
    "img_Importance": 103,
    "Label1": 78,
    "Label2": 10,
    "Label2_1": 5,
    "Label3": 133,
    "Label3_1": 147,
    "Label3_2": 134,
    "Label3_3": 135,
    "lbl_ActionDetail": 121,
    "lbl_ActionTarget": 114,
    "lbl_ActionText": 96,
    "lbl_AppRelease": 55,
    "lbl_DialogTitle_1": 51,
    "lbl_DialogTitle_2": 68,
    "lbl_Heading1_1": 14,
    "lbl_Heading1_2": 178,
    "lbl_Heading2_1": 13,
    "lbl_Heading2_2": 180,
    "lbl_Heading3_1": 16,
    "lbl_Heading3_2": 182,
    "lbl_LatestPost": 116,
    "lbl_PrimaryText_1": 12,
    "lbl_PrimaryText_2": 179,
    "lbl_PrimaryText_3": 168,
    "lbl_PrimaryText_4": 113,
    "lbl_PrimaryText_5": 73,
    "lbl_PrimaryText_6": 129,
    "lbl_PrimaryText_7": 171,
    "lbl_PrimaryText_8": 202,
    "lbl_PrimaryText_9": 203,
    "lbl_SecondaryText_1": 15,
    "lbl_SecondaryText_10": 163,
    "lbl_SecondaryText_11": 159,
    "lbl_SecondaryText_12": 69,
    "lbl_SecondaryText_13": 72,
    "lbl_SecondaryText_14": 128,
    "lbl_SecondaryText_15": 130,
    "lbl_SecondaryText_16": 138,
    "lbl_SecondaryText_2": 183,
    "lbl_SecondaryText_22": 140,
    "lbl_SecondaryText_3": 150,
    "lbl_SecondaryText_4": 153,
    "lbl_SecondaryText_5": 155,
    "lbl_SecondaryText_6": 157,
    "lbl_SecondaryText_7": 169,
    "lbl_SecondaryText_8": 165,
    "lbl_SecondaryText_9": 166,
    "Loading": 54,
    "LoadingSpinner_v1__": 6,
    "LoadingSpinner_v1___1": 59,
    "ProgressHistory": 125,
    "ProgressHistoryPanel": 126,
    "rad_EditImportance": 154,
    "rad_RadioButtons_1": 26,
    "rad_RadioButtons_2": 194,
    "rect_DialogBackdrop_1": 53,
    "rect_DialogBackdrop_2": 76,
    "Screen2": 177,
    "separator": 136,
    "separator_1": 137,
    "shadowRectangle_3": 43,
    "ShadowRectangle_v2__": 35,
    "ShadowRectangle_v2___1": 149,
    "ShadowRectangle_v2___2": 67,
    "ShadowRectangle_v2___3": 127,
    "slide_Slider_1": 28,
    "slide_Slider_2": 92,
    "slide_Slider_3": 196,
    "TH": 81,
    "th_2": 84,
    "th_3": 85,
    "th_4": 86,
    "th_5": 88,
    "th_6": 89,
    "th_7": 90,
    "th_ActionText": 82,
    "Ticker_2": 38,
    "Timer1": 7,
    "TimerHide_2": 41,
    "TimerHold_2": 40,
    "TimerShow_2": 39,
    "Toast_v2__": 37,
    "Toast_v2___1": 145,
    "tog_Toggle_1": 29,
    "tog_Toggle_2": 197,
    "tog_WrapActionText": 83,
    "txt_BasicTextEdit_1": 32,
    "txt_BasicTextEdit_2": 200,
    "txt_BasicTextEdit_3": 139,
    "txt_EditActionDetail": 156,
    "txt_EditActionText": 151,
    "txt_ExternalOwners": 160,
    "txt_NewPost": 118,
    "txt_RequestClosureEvidence": 70,
    "txt_RichTextEditor_1": 34,
    "txt_RichTextEditor_2": 201
  },
  "FunctionParamsInvariantScripts": {
    "EmailFns_v1__.Builder_Params": [
      "{\r\n    To: \"jonathan.warman@apacheix.co.uk\", \r\n    Subject: \"Test Email\", \r\n    Header: \"\",\r\n    Content: \"\r\n        <p>Put your email content here.\r\n    \",\r\n    MinWidth: 550\r\n}",
      "{\r\n    To: \"jonathan.warman@apacheix.co.uk\", \r\n    Subject: \"Test Email\", \r\n    Header: \"Contextual header\",\r\n    Content: \"\r\n        <p>Put your email content here.\r\n    \",\r\n    MinWidth: 550\r\n}"
    ]
  },
  "FunctionParamsInvariantScriptsOnInstances": {
    "EmailFn.Builder_Params": [
      "{\r\n    To: \"jonathan.warman@apacheix.co.uk\", \r\n    Subject: \"Test Email\", \r\n    Header: \"\",\r\n    Content: \"\r\n        <p>Put your email content here.\r\n    \",\r\n    MinWidth: 550\r\n}",
      "{\r\n    To: \"jonathan.warman@apacheix.co.uk\", \r\n    Subject: \"Test Email\", \r\n    Header: \"Contextual header\",\r\n    Content: \"\r\n        <p>Put your email content here.\r\n    \",\r\n    MinWidth: 550\r\n}"
    ]
  },
  "HeaderLastSavedDateTimeUTC": "10/10/2022 17:37:11",
  "IsLegacyComponentAllowGlobalScopeCase": false,
  "LocalConnectionIDReferences": {
    "9901563c-93f2-4716-b0c3-eff3116c8fdd": "\"/providers/microsoft.powerapps/apis/shared_sharepointonline/connections/63817a258eb74e5eb0a06e57ff801f6c\"",
    "d332acba-c37a-4f9a-a6f0-4e1e9d31ac50": "\"/providers/microsoft.powerapps/apis/shared_office365/connections/98adda3697f74991a4b2f7162f08020c\"",
    "e7c7eaf6-ea68-474a-9b4b-881e341ac0a1": "\"/providers/microsoft.powerapps/apis/shared_office365users/connections/81ea854a9dd24a98b5e219ed99cfd21d\""
  },
  "LocalDatabaseReferencesAsEmpty": false,
  "LocalResourceFileNames": {
    "Apache Logo - Feather": "15b7430d-fc7a-4dbd-bcdb-d7686732424c.png",
    "CustomLoadingSpinner": "af140cd3-82d4-4c91-8add-e7d4e40c2f85.gif"
  },
  "LocalResourceRootPaths": {
    "Apache Logo - Feather": "https://docserverpwaprodsuk.blob.core.windows.net/ab2a8a70-6f6f-41da-a275-3448d9da2652-1/resource/Assets0Images015b7430d-fc7a-4dbd-bcdb-d7686732424c.png?sv=2017-04-17&sr=b&sig=BlvwjCX1wJJa1vGEpaulkgcv9zteRnmxYBdugGgw1%2B0%3D&spr=https&se=2022-10-11T17%3A40%3A51Z&sp=r",
    "CustomLoadingSpinner": "https://docserverpwaprodsuk.blob.core.windows.net/ab2a8a70-6f6f-41da-a275-3448d9da2652-1/resource/Assets0Images0af140cd3-82d4-4c91-8add-e7d4e40c2f85.gif?sv=2017-04-17&sr=b&sig=jfu2gzvQIGkuqCfvIEvG4v2vXPpoNjd2igISAxuePLk%3D&spr=https&se=2022-10-11T17%3A40%3A51Z&sp=r"
  },
  "OrderComponentMetadata": {
    "0797ce7b40814da9b60d9b533fbb8cab": 0,
    "11534f0b235c4c829c75bbec5207973e": 5,
    "37ad2fc234c34df0bb283b66e46cd983": 2,
    "712ff2a93a474f9b85e9644ca20c4c06": 1,
    "c558d601e60f4fd8acbd25a85897c997": 4,
    "d5916f6b45d8489d8f1d43c18d89253e": 3
  },
  "OrderComponentTemplate": {
    "0797ce7b40814da9b60d9b533fbb8cab": 0,
    "11534f0b235c4c829c75bbec5207973e": 5,
    "37ad2fc234c34df0bb283b66e46cd983": 2,
    "712ff2a93a474f9b85e9644ca20c4c06": 1,
    "c558d601e60f4fd8acbd25a85897c997": 4,
    "d5916f6b45d8489d8f1d43c18d89253e": 3
  },
  "OrderDataSource": {
    "Actions": 6,
    "ComboBoxSample": 4,
    "CustomGallerySample": 5,
    "DropDownSample": 3,
    "g_ListOfClosers": 8,
    "Office365Outlook": 0,
    "Office365Users": 1,
    "People": 7,
    "RadioSample": 2
  },
  "OrderGroupControls": {},
  "OrderPcfTemplate": {},
  "OrderTemplate": {},
  "OrderXMLTemplate": {
    "button": 1,
    "checkbox": 12,
    "combobox": 17,
    "datepicker": 13,
    "dropdown": 16,
    "gallery": 11,
    "groupContainer": 3,
    "htmlViewer": 5,
    "icon": 9,
    "image": 4,
    "label": 0,
    "radio": 14,
    "rectangle": 7,
    "richTextEditor": 15,
    "slider": 10,
    "text": 6,
    "timer": 2,
    "toggleSwitch": 8
  },
  "PublishOrderIndices": {
    "App": 0,
    "btn_AcceptOwnership": 51,
    "btn_BigDanger_1": 170,
    "btn_BigDanger_2": 128,
    "btn_CancelRequestClosure": 9,
    "btn_CancelRequestedOwner": 78,
    "btn_CollapseAction": 34,
    "btn_ConfirmClosure": 54,
    "btn_ConfirmRequestClosure": 10,
    "btn_DeleteAction": 69,
    "btn_DialogCancel_1": 188,
    "btn_Edit_1": 22,
    "btn_EditAction": 32,
    "btn_EditCancel": 91,
    "btn_EditUpdate": 93,
    "btn_ExpandAction": 33,
    "btn_HomeAddAction": 14,
    "btn_LittleDanger_1": 171,
    "btn_LittleDanger_2": 131,
    "btn_Primary_1": 167,
    "btn_Primary_2": 129,
    "btn_Primary_4": 123,
    "btn_ProgressHistoryCancel": 110,
    "btn_ProgressHistoryDone": 111,
    "btn_QuickPostSend": 46,
    "btn_RejectClosure": 55,
    "btn_RejectOwnership": 52,
    "btn_ReOpen": 92,
    "btn_Secondary_1": 168,
    "btn_Secondary_2": 130,
    "btn_Tertiary_1": 169,
    "btn_Tertiary_2": 127,
    "btn_THExpandQuickPost": 26,
    "Button2": 159,
    "chk_ActionStatus": 37,
    "chk_XYZ_4": 173,
    "chk_XYZ_5": 174,
    "chk_XYZ_6": 175,
    "chk_XYZ_7": 133,
    "chk_XYZ_8": 134,
    "chk_XYZ_9": 135,
    "Container1": 146,
    "Container1_3": 156,
    "Container6": 30,
    "Controls": 0,
    "date_DatePicker_1": 183,
    "date_DatePicker_2": 141,
    "date_EditTarget": 90,
    "date_EditTarget_1": 109,
    "debug": 57,
    "dev_NavigateHome_2": 120,
    "dev_NavigateLoading_2": 60,
    "dev_StartLoading_2": 61,
    "dialog_AskSomething_1": 186,
    "dialog_RequestClosure": 1,
    "Dialogs": 0,
    "Dialogs_1": 185,
    "Dialogs_2": 0,
    "drop_EditCloser": 84,
    "drop_EditOwner": 79,
    "drop_MultiSelect_1": 181,
    "drop_MultiSelect_2": 142,
    "drop_Standard_1": 180,
    "drop_Standard_2": 138,
    "Edit": 0,
    "EditPanel": 65,
    "EmailFn": 119,
    "EmailFns_v1__": 0,
    "fn_EditActionSendEmails": 63,
    "fn_InitAppSpecificsAndFinish": 118,
    "fn_InitColors": 114,
    "fn_InitControls": 115,
    "fn_InitCore": 113,
    "fn_InitFrame": 117,
    "Gallery1": 28,
    "Gallery2": 99,
    "galleryTemplate1": 29,
    "galleryTemplate2": 100,
    "grp_Checkboxes_1": 172,
    "grp_Checkboxes_2": 132,
    "grp_Closer": 81,
    "grp_ExternalOwner": 75,
    "grp_LatestPost": 44,
    "grp_MainGallary": 15,
    "grp_OtherActionsAcceptOwnership": 49,
    "grp_OtherActionsConfirmClosure": 53,
    "grp_OtherInfo": 36,
    "grp_Owner": 38,
    "grp_Progress": 87,
    "Home": 0,
    "HtmlText1": 59,
    "HtmlText2": 149,
    "HtmlText2_3": 161,
    "Icon1": 40,
    "Icon1_3": 160,
    "Icon3_1": 177,
    "Icon3_2": 136,
    "Icon3_3": 89,
    "Icon5_2": 158,
    "Image1": 147,
    "Image1_1": 151,
    "Image1_4": 39,
    "Image1_5": 41,
    "Image1_6": 6,
    "Image1_7": 12,
    "img_Closer": 48,
    "img_Importance": 35,
    "Label1": 13,
    "Label2": 148,
    "Label2_1": 150,
    "Label3": 101,
    "Label3_1": 64,
    "Label3_2": 102,
    "Label3_3": 103,
    "lbl_ActionDetail": 58,
    "lbl_ActionTarget": 43,
    "lbl_ActionText": 31,
    "lbl_AppRelease": 112,
    "lbl_DialogTitle_1": 187,
    "lbl_DialogTitle_2": 3,
    "lbl_Heading1_1": 164,
    "lbl_Heading1_2": 121,
    "lbl_Heading2_1": 163,
    "lbl_Heading2_2": 122,
    "lbl_Heading3_1": 166,
    "lbl_Heading3_2": 124,
    "lbl_LatestPost": 45,
    "lbl_PrimaryText_1": 162,
    "lbl_PrimaryText_2": 125,
    "lbl_PrimaryText_3": 85,
    "lbl_PrimaryText_4": 42,
    "lbl_PrimaryText_5": 8,
    "lbl_PrimaryText_6": 97,
    "lbl_PrimaryText_7": 88,
    "lbl_PrimaryText_8": 50,
    "lbl_PrimaryText_9": 56,
    "lbl_SecondaryText_1": 165,
    "lbl_SecondaryText_10": 80,
    "lbl_SecondaryText_11": 76,
    "lbl_SecondaryText_12": 4,
    "lbl_SecondaryText_13": 7,
    "lbl_SecondaryText_14": 96,
    "lbl_SecondaryText_15": 98,
    "lbl_SecondaryText_16": 106,
    "lbl_SecondaryText_2": 126,
    "lbl_SecondaryText_22": 108,
    "lbl_SecondaryText_3": 67,
    "lbl_SecondaryText_4": 70,
    "lbl_SecondaryText_5": 72,
    "lbl_SecondaryText_6": 74,
    "lbl_SecondaryText_7": 86,
    "lbl_SecondaryText_8": 82,
    "lbl_SecondaryText_9": 83,
    "Loading": 0,
    "LoadingSpinner_v1__": 0,
    "LoadingSpinner_v1___1": 116,
    "ProgressHistory": 0,
    "ProgressHistoryPanel": 94,
    "rad_EditImportance": 71,
    "rad_RadioButtons_1": 176,
    "rad_RadioButtons_2": 137,
    "rect_DialogBackdrop_1": 189,
    "rect_DialogBackdrop_2": 11,
    "Screen2": 0,
    "separator": 104,
    "separator_1": 105,
    "shadowRectangle_3": 157,
    "ShadowRectangle_v2__": 0,
    "ShadowRectangle_v2___1": 66,
    "ShadowRectangle_v2___2": 2,
    "ShadowRectangle_v2___3": 95,
    "slide_Slider_1": 178,
    "slide_Slider_2": 27,
    "slide_Slider_3": 139,
    "TH": 16,
    "th_2": 19,
    "th_3": 20,
    "th_4": 21,
    "th_5": 23,
    "th_6": 24,
    "th_7": 25,
    "th_ActionText": 17,
    "Ticker_2": 152,
    "Timer1": 145,
    "TimerHide_2": 155,
    "TimerHold_2": 154,
    "TimerShow_2": 153,
    "Toast_v2__": 0,
    "Toast_v2___1": 62,
    "tog_Toggle_1": 179,
    "tog_Toggle_2": 140,
    "tog_WrapActionText": 18,
    "txt_BasicTextEdit_1": 182,
    "txt_BasicTextEdit_2": 143,
    "txt_BasicTextEdit_3": 107,
    "txt_EditActionDetail": 73,
    "txt_EditActionText": 68,
    "txt_ExternalOwners": 77,
    "txt_NewPost": 47,
    "txt_RequestClosureEvidence": 5,
    "txt_RichTextEditor_1": 184,
    "txt_RichTextEditor_2": 144
  },
  "ResourcesJsonIndices": {
    "Image-Apache Logo - Feather": 2,
    "Image-CustomLoadingSpinner": 1,
    "Image-SampleImage": 0
  },
  "RuleScreenIdWithoutScreen": {},
  "TemplateVersions": {},
  "VolatileProperties": {
    "AnalysisLoadTime": 2.2754025,
    "ControlCount": {
      "0797ce7b40814da9b60d9b533fbb8cab": 2,
      "11534f0b235c4c829c75bbec5207973e": 1,
      "37ad2fc234c34df0bb283b66e46cd983": 1,
      "712ff2a93a474f9b85e9644ca20c4c06": 2,
      "button": 38,
      "c558d601e60f4fd8acbd25a85897c997": 2,
      "checkbox": 7,
      "combobox": 2,
      "d5916f6b45d8489d8f1d43c18d89253e": 4,
      "datepicker": 4,
      "dropdown": 4,
      "gallery": 2,
      "galleryTemplate": 2,
      "groupContainer": 21,
      "htmlViewer": 4,
      "icon": 10,
      "image": 9,
      "label": 53,
      "radio": 3,
      "rectangle": 4,
      "richTextEditor": 3,
      "screen": 5,
      "slider": 3,
      "text": 7,
      "timer": 5,
      "toggleSwitch": 3
    },
    "DeserializationLoadTime": 4.3612613,
    "ErrorCount": 1992
  },
  "WasLocalDatabaseReferencesEmpty": true
}